{"type":"FeatureCollection","features":[{"type":"Feature","id":1,"geometry":{"type":"Point","coordinates":[-73.239250182999967,44.195980072000054,0]},"properties":{"OBJECTID":1,"FacilityID":"1,134","FacilityName":"Powhatan Ferrisburgh","DesignHydraulicCapacityInMGD":"0.12","SeptageReceivedAtThisFacility":"N","Latitude":"44.1960","Longitude":"-73.2393","PermitID":"3-1543","PermitteeName":"Powhatan LLC","ProgramCategory":"Industrial Discharge","NPDESPermitNumber":"VT0001473","https://anrweb.vt.gov/PubDocs/DEC/WSMD/Wastewater/permits/3-1543/3-1543.pdf":null}}]}