{"type":"FeatureCollection","features":[{"type":"Feature","id":0,"geometry":{"type":"Point","coordinates":[-72.707820049999953,44.312674401000038,0]},"properties":{"OBJECTID":0,"FacilityID":"283","Facility Name":"Moretown Landfill","Design Hydraulic Capacity In MGD":"0.12","Septage Received At This Facility":"N","Latitude":"44.3127","Longitude":"-72.7078","PermitID":"3-1357","Permittee Name":"Moretown Landfill Inc","Program Category":"Pretreatment Discharge","NPDES Permit Number":"3-1357","Permit Link ":"https://anrweb.vt.gov/PubDocs/DEC/WSMD/Wastewater/Permits/3-1357/Permit.3-1357.20131023.pdf"}}]}