{"type":"FeatureCollection","features":[{"type":"Feature","id":1,"geometry":{"type":"Point","coordinates":[-73.233481999999981,44.895660000000078,0]},"properties":{"OBJECTID":1,"FacilityID":"213","FacilityName":"North Hero Water Treatment Plant","DesignHydraulicCapacityInMGD":"0.06","SeptageReceivedAtThisFacility":"N","Latitude":"44.8957","Longitude":"-73.2335","PermitID":"3-1414","PermitteeName":"Town of North Hero","ProgramCategory":"Industrial Discharge","NPDESPermitNumber":"VT0101231","https://anrweb.vt.gov/PubDocs/DEC/WSMD/Wastewater/permits/3-1414/3-1414.pdf":null}}]}