{"type":"FeatureCollection","features":[{"type":"Feature","id":1,"geometry":{"type":"Point","coordinates":[-73.096537739529978,44.69898305808232]},"properties":{"OBJECTID":1,"FacilityID":"117","FacilityName":"P B M Nutritionals Inc","DesignHydraulicCapacityInMGD":"0.43","SeptageReceivedAtThisFacility":"N","Latitude":"44.6990","Longitude":"-73.0965","PermitID":"3-1209","PermitteeName":"PBM Nutritionals Inc","ProgramCategory":"Industrial Discharge","NPDESPermitNumber":"VT0020702","PermitLink":"https://anrweb.vt.gov/ANR/vtANR/DocBrowser.aspx?Directory=DEC/WSMD/Wastewater/permits/3-1209/"}}]}