{"type":"FeatureCollection","features":[{"type":"Feature","id":0,"geometry":{"type":"Point","coordinates":[-73.305633365985287,43.800356537447605,0]},"properties":{"OBJECTID":0,"Facility Name":"Orwell","Design Hydraulic Capacity In MGD":"0.03","Septage Received At This Facility":"Y","Permit ID":"3-1214","Permittee Name":"Town of Orwell","Program Category":"Municipal Discharge","NPDES Permit Number":"VT0100676","Permit Record ID":null,"Permit Link":null}}]}