{"type":"FeatureCollection","features":[{"type":"Feature","id":1,"geometry":{"type":"Point","coordinates":[-72.577766545999964,43.249901217000058,0]},"properties":{"OBJECTID":1,"FacilityID":"2,238","FacilityName":"Drews LLC","DesignHydraulicCapacityInMGD":"0.01","SeptageReceivedAtThisFacility":"N","Latitude":"43.2499","Longitude":"-72.5778","PermitID":"3-1561","PermitteeName":"Drews LLC","ProgramCategory":"Pretreatment Discharge","NPDESPermitNumber":"","https://anrweb.vt.gov/PubDocs/DEC/WSMD/Wastewater/Permits/3-1561/Permit.3-1561.20151001.pdf":null}}]}