{"type":"FeatureCollection","features":[{"type":"Feature","id":0,"geometry":{"type":"Point","coordinates":[-72.622118999999941,43.825095000000033]},"properties":{"OBJECTID":0,"Facility Name":"Bethel","Design Hydraulic Capacity In MGD":"0.23","Septage Received At This Facility":"N","PermitID":"3-1280","Permittee Name":"Town of Bethel","Program Category":"Municipal Discharge","NPDES Permit Number":"VT0100048","Permit Link":"https://anrweb.vt.gov/ANR/vtANR/DocBrowser.aspx?Directory=DEC/WSMD/Wastewater/permits/3-1280/"}}]}