{"type":"FeatureCollection","features":[{"type":"Feature","id":1,"geometry":{"type":"Point","coordinates":[-73.007959999744813,44.857812000239839]},"properties":{"OBJECTID":1,"FacilityID":"179","FacilityName":"Bourbeau Aggregate, LLC","DesignHydraulicCapacityInMGD":"0.00","SeptageReceivedAtThisFacility":"N","Latitude":"44.8578","Longitude":"-73.0080","PermitID":"3-1469","PermitteeName":"Bourbeau Aggregate, LLC","ProgramCategory":"Industrial Discharge","NPDESPermitNumber":"VT0000906","PermitLink":"https://anrweb.vt.gov/ANR/vtANR/DocBrowser.aspx?Directory=DEC/WSMD/Wastewater/permits/3-1469/"}},{"type":"Feature","id":2,"geometry":{"type":"Point","coordinates":[-73.162294105325927,44.914106949607948]},"properties":{"OBJECTID":2,"FacilityID":"224","FacilityName":"Swanton Village Water Treatment Plant","DesignHydraulicCapacityInMGD":"0.14","SeptageReceivedAtThisFacility":"N","Latitude":"44.9141","Longitude":"-73.1623","PermitID":"3-0334","PermitteeName":"Village of Swanton","ProgramCategory":"Industrial Discharge","NPDESPermitNumber":"VT0020877","PermitLink":"https://anrweb.vt.gov/ANR/vtANR/DocBrowser.aspx?Directory=DEC/WSMD/Wastewater/permits/3-0334/"}},{"type":"Feature","id":3,"geometry":{"type":"Point","coordinates":[-73.136919737469242,44.924186404298219]},"properties":{"OBJECTID":3,"FacilityID":"92","FacilityName":"Swanton","DesignHydraulicCapacityInMGD":"0.90","SeptageReceivedAtThisFacility":"N","Latitude":"44.9242","Longitude":"-73.1369","PermitID":"3-1292","PermitteeName":"Town of Swanton","ProgramCategory":"Municipal Discharge","NPDESPermitNumber":"VT0100501","PermitLink":"https://anrweb.vt.gov/ANR/vtANR/DocBrowser.aspx?Directory=DEC/WSMD/Wastewater/permits/3-1292/"}}]}