{"type":"FeatureCollection","features":[{"type":"Feature","id":0,"geometry":{"type":"Point","coordinates":[-72.428046536999943,44.275945724000053,0]},"properties":{"OBJECTID":0,"FacilityID":"84","Facility Name":"Plainfield","Design Hydraulic Capacity In MGD":"0.25","Septage Received At This Facility":"N","Latitude":"44.2759","Longitude":"-72.4280","PermitID":"3-0381","Permittee Name":"Town of Plainfield","Program Category":"Municipal Discharge","NPDES Permit Number":"VT0100781","Permit Link ":"https://anrweb.vt.gov/PubDocs/DEC/WSMD/Wastewater/permits/3-0381/3-0381.pdf"}}]}