{"type":"FeatureCollection","features":[{"type":"Feature","id":0,"geometry":{"type":"Point","coordinates":[-72.600304930999982,44.254945753000072]},"properties":{"OBJECTID":0,"FacilityID":"9","FacilityName":"Montpelier","DesignHydraulicCapacityInMGD":"3.97","SeptageReceivedAtThisFacility":"Y","Latitude":"44.2549","Longitude":"-72.6003","PermitID":"3-1207","PermitRecordID":"37","PermitteeName":"City of Montpelier","ProgramCategory":"Municipal Discharge","NPDESPermitNumber":"VT0100196","Permit Link":"https://anrweb.vt.gov/ANR/vtANR/DocBrowser.aspx?Directory=DEC/WSMD/Wastewater/permits/3-1400/"}},{"type":"Feature","id":0,"geometry":{"type":"Point","coordinates":[-72.572410418999937,44.27704585400005]},"properties":{"OBJECTID":0,"FacilityID":"547","FacilityName":"Montpelier Swimming Pool","DesignHydraulicCapacityInMGD":"0.00","SeptageReceivedAtThisFacility":"N","Latitude":"44.2770","Longitude":"-72.5724","PermitID":"3-1338","PermitRecordID":"458","PermitteeName":"City of Montpelier","ProgramCategory":"Industrial Discharge","NPDESPermitNumber":"VT0001066","Permit Link":"https://anrweb.vt.gov/ANR/vtANR/DocBrowser.aspx?Directory=DEC/WSMD/Wastewater/permits/3-1338/"}}]}