{"type":"FeatureCollection","features":[{"type":"Feature","id":1,"geometry":{"type":"Point","coordinates":[-72.685071999999934,44.635266000000058,0]},"properties":{"OBJECTID":1,"FacilityID":"76","FacilityName":"Johnson","DesignHydraulicCapacityInMGD":"0.27","SeptageReceivedAtThisFacility":"N","Latitude":"44.6353","Longitude":"-72.6851","PermitID":"3-1149","PermitteeName":"Village of Johnson","ProgramCategory":"Municipal Discharge","NPDESPermitNumber":"VT0100901","https://anrweb.vt.gov/PubDocs/DEC/WSMD/Wastewater/permits/3-1149/3-1149.pdf":null}}]}