{"type":"FeatureCollection","features":[{"type":"Feature","id":1,"geometry":{"type":"Point","coordinates":[-73.302406668999936,44.647956043000079,0]},"properties":{"OBJECTID":1,"FacilityID":"190","FacilityName":"South Hero Fire District 4","DesignHydraulicCapacityInMGD":"0.01","SeptageReceivedAtThisFacility":"N","Latitude":"44.6480","Longitude":"-73.3024","PermitID":"3-0230","PermitteeName":"South Hero Fire District #4","ProgramCategory":"Industrial Discharge","NPDESPermitNumber":"VT0101273","https://anrweb.vt.gov/PubDocs/DEC/WSMD/Wastewater/permits/3-0230/3-0230.pdf":null}}]}