{"type":"FeatureCollection","features":[{"type":"Feature","id":1,"geometry":{"type":"Point","coordinates":[-72.678704899398895,43.392116000008912]},"properties":{"OBJECTID":1,"FacilityID":"43","FacilityName":"Ludlow","DesignHydraulicCapacityInMGD":"1.05","SeptageReceivedAtThisFacility":"N","Latitude":"43.3921","Longitude":"-72.6787","PermitID":"3-1208","PermitteeName":"Village of Ludlow","ProgramCategory":"Municipal Discharge","NPDESPermitNumber":"VT0100145","PermitLink":"https://anrweb.vt.gov/ANR/vtANR/DocBrowser.aspx?Directory=DEC/WSMD/Wastewater/permits/3-1208/"}},{"type":"Feature","id":2,"geometry":{"type":"Point","coordinates":[-72.67209625176028,43.38063812313851]},"properties":{"OBJECTID":2,"FacilityID":"536","FacilityName":"Magris Talc USA, Inc - Argonaut Mine","DesignHydraulicCapacityInMGD":"0.00","SeptageReceivedAtThisFacility":"N","Latitude":"43.3806","Longitude":"-72.6721","PermitID":"3-0348","PermitteeName":"Magris Talc USA, Inc.","ProgramCategory":"Industrial Discharge","NPDESPermitNumber":"VT0001023","PermitLink":"https://anrweb.vt.gov/ANR/vtANR/DocBrowser.aspx?Directory=DEC/WSMD/Wastewater/permits/3-0348/"}},{"type":"Feature","id":3,"geometry":{"type":"Point","coordinates":[-72.662420000604484,43.382580000024554]},"properties":{"OBJECTID":3,"FacilityID":"859","FacilityName":"Imerys Talc - Rainbow Mine","DesignHydraulicCapacityInMGD":"0.43","SeptageReceivedAtThisFacility":"N","Latitude":"43.3826","Longitude":"-72.6624","PermitID":"3-1506","PermitteeName":"Imerys Talc Vermont Inc","ProgramCategory":"Industrial Discharge","NPDESPermitNumber":"VT0001163","PermitLink":"https://anrweb.vt.gov/ANR/vtANR/DocBrowser.aspx?Directory=DEC/WSMD/Wastewater/permits/3-1506/"}}]}