{"type":"FeatureCollection","features":[{"type":"Feature","id":0,"geometry":{"type":"Point","coordinates":[-72.376266799999939,44.515253900000062]},"properties":{"OBJECTID":0,"Facility ID":"73","Facility Name":"Hardwick","Design Hydraulic Capacity In MGD":"0.37","Septage Received At This Facility":"N","Permit ID":"3-1143","Permit Record ID":"24","Permittee Name":"Town of Hardwick","Program Category":"Municipal Discharge","NPDES Permit Number":"VT0100137","Permit Link":"https://anrweb.vt.gov/ANR/vtANR/DocBrowser.aspx?Directory=DEC/WSMD/Wastewater/permits/3-1143/"}}]}