{"type":"FeatureCollection","features":[{"type":"Feature","id":0,"geometry":{"type":"Point","coordinates":[-72.32928099999998,44.390875000000051,0]},"properties":{"OBJECTID":0,"FacilityID":"198","Facility Name":"Cabot","Design Hydraulic Capacity In MGD":"0.10","Septage Received At This Facility":"N","Latitude":"44.3909","Longitude":"-72.3293","PermitID":"3-1440","Permittee Name":"Town of Cabot","Program Category":"Municipal Discharge","NPDES Permit Number":"VT0101257","Permit Link ":"https://anrweb.vt.gov/PubDocs/DEC/WSMD/Wastewater/permits/3-1440/3-1440.pdf"}}]}