{"type":"FeatureCollection","features":[{"type":"Feature","id":1,"geometry":{"type":"Point","coordinates":[-72.398299999999949,43.441414000000066,0]},"properties":{"OBJECTID":1,"FacilityID":"98","FacilityName":"Windsor Weston Heights","DesignHydraulicCapacityInMGD":"0.02","SeptageReceivedAtThisFacility":"N","Latitude":"43.4414","Longitude":"-72.3983","PermitID":"3-1168","PermitteeName":"Town of Windsor","ProgramCategory":"Municipal Discharge","NPDESPermitNumber":"VT0100447","https://anrweb.vt.gov/PubDocs/DEC/WSMD/Wastewater/permits/3-1168/3-1168.pdf":null}}]}